{"slide_id": "20d95200c4abf876205b85c17f55b2d3-FAIR_and_Open_D__s7__G6_MARGIN_VIOLATION", "width": 1280, "height": 720, "elements": [{"element_id": "shp148", "type": "body", "bbox": {"x": 0.0, "y": 0.0, "width": 1280.0, "height": 117.03}, "text": "Is Open Data Equal to Free Data?", "style": {"font_size_pt": 44.0}, "z": 0, "placeholder_id": null, "metadata": {}}, {"element_id": "shp149", "type": "body", "bbox": {"x": 1015.41, "y": 698.53, "width": 274.29, "height": 22.62}, "text": "Icons made by https://www.flaticon.com/authors/eucalyp", "style": {"font_size_pt": 8.0}, "z": 1, "placeholder_id": null, "metadata": {}}, {"element_id": "shp150", "type": "body", "bbox": {"x": 22.3, "y": 144.78, "width": 389.81, "height": 140.24}, "text": "This question can be interpreted in a number of ways are open data free to use, are they free to acquire and is there a cost to their proper management?", "style": {"font_size_pt": 16.0, "color": "#595959"}, "z": 2, "placeholder_id": null, "metadata": {}}, {"element_id": "shp151", "type": "image", "bbox": {"x": 128.26, "y": 295.31, "width": 177.9, "height": 177.9}, "text": "", "style": {}, "z": 3, "placeholder_id": null, "metadata": {}}, {"element_id": "shp152", "type": "body", "bbox": {"x": 448.86, "y": 135.28, "width": 612.85, "height": 300.51}, "text": "On the other hand, when taking financial considerations into account, there can be times when you can acquire data for a fee that you must then be careful to read their terms and conditions carefully. \n\nIn many cases, this method of acquiring data will be licensed using bespoke licences which may at first glance look very similar to licences such as CC but will have significant variations which ties back into their freeness to use.", "style": {"font_size_pt": 18.0}, "z": 4, "placeholder_id": null, "metadata": {}}, {"element_id": "shp153", "type": "image", "bbox": {"x": 1061.71, "y": 130.43, "width": 194.15, "height": 194.15}, "text": "", "style": {}, "z": 5, "placeholder_id": null, "metadata": {}}, {"element_id": "shp154", "type": "body", "bbox": {"x": 415.41, "y": 402.42, "width": 679.76, "height": 307.42}, "text": "An example here is the data that can be acquired from the British Geological Survey (BGS). In some cases, data may only be acquired for a fee and the BGS has its own license which you would need to adhere to. Another example can be found at the UK’s Meteorological Office, while many organisations in the UK have also adopted the Open Government Licence (OGL).", "style": {"font_size_pt": 14.0, "color": "#3A3838"}, "z": 6, "placeholder_id": null, "metadata": {}}, {"element_id": "shp155", "type": "image", "bbox": {"x": 827.86, "y": 620.48, "width": 214.56, "height": 66.74}, "text": "", "style": {}, "z": 7, "placeholder_id": null, "metadata": {}}], "metadata": {"scene": "full_proposal", "source": "zenodo10k"}}