{"slide_id": "800d590999c12cc29efec87123d9234a-uc-cesjune9fina__s9__G6_MARGIN_VIOLATION", "width": 1058, "height": 794, "elements": [{"element_id": "shp146", "type": "body", "bbox": {"x": 380.69, "y": 1815.86, "width": 16.91, "height": 3309.58}, "text": "This project  has received funding from the European Union's Horizon 2020 research and innovation programme under grant agreement No. 787829.", "style": {"font_size_pt": 18.0, "color": "#7F7F7F"}, "z": 0, "placeholder_id": null, "metadata": {}}, {"element_id": "shp147", "type": "image", "bbox": {"x": 188.69, "y": 455.82, "width": 117.62, "height": 66.16}, "text": "", "style": {}, "z": 1, "placeholder_id": null, "metadata": {}}, {"element_id": "shp148", "type": "image", "bbox": {"x": 704.17, "y": 0.0, "width": 354.17, "height": 427.0}, "text": "", "style": {}, "z": 2, "placeholder_id": null, "metadata": {}}, {"element_id": "shp149", "type": "image", "bbox": {"x": 767.38, "y": 646.52, "width": 268.5, "height": 136.17}, "text": "", "style": {}, "z": 3, "placeholder_id": null, "metadata": {}}, {"element_id": "shp150", "type": "body", "bbox": {"x": 57.5, "y": 22.83, "width": 749.06, "height": 558.84}, "text": "www.uc.pt/supera\nwww.superaproject.eu\n\nEmail: monica@ces.uc.pt\nTel: +351 239 855 570\n\n @superaproject \n#SuperaH2020\n/superaproject", "style": {"font_size_pt": 35.0, "color": "#999999"}, "z": 4, "placeholder_id": null, "metadata": {}}, {"element_id": "shp151", "type": "image", "bbox": {"x": 70.59, "y": 644.41, "width": 117.0, "height": 117.0}, "text": "", "style": {}, "z": 5, "placeholder_id": null, "metadata": {}}, {"element_id": "shp152", "type": "image", "bbox": {"x": 220.64, "y": 381.45, "width": 66.0, "height": 66.17}, "text": "", "style": {}, "z": 6, "placeholder_id": null, "metadata": {}}, {"element_id": "shp153", "type": "shape", "bbox": {"x": 16.33, "y": -15.17, "width": 32.0, "height": 32.0}, "text": "", "style": {}, "z": 7, "placeholder_id": null, "metadata": {}}, {"element_id": "shp154", "type": "image", "bbox": {"x": 220.77, "y": 529.52, "width": 62.04, "height": 62.04}, "text": "", "style": {}, "z": 8, "placeholder_id": null, "metadata": {}}, {"element_id": "shp155", "type": "body", "bbox": {"x": 204.26, "y": 625.71, "width": 502.5, "height": 145.0}, "text": "This project  has received funding from the European Union's Horizon 2020 research and innovation programme under grant agreement No. 787829.", "style": {"font_size_pt": 18.0, "color": "#7F7F7F"}, "z": 9, "placeholder_id": null, "metadata": {}}], "metadata": {"scene": "full_proposal", "source": "zenodo10k"}}